MANIFEST.in
README.md
setup.cfg
setup.py
src/__init__.py
src/main.py
src/cli/__init__.py
src/cli/cli.py
src/cli/common.py
src/cli/irancell.py
src/config/__init__.py
src/config/config_default.yaml
src/models/__init__.py
src/models/enums.py
src/models/offer.py
src/services/__init__.py
src/services/base.py
src/services/irancell/__init__.py
src/services/irancell/config.py
src/services/irancell/irancell.py
src/services/irancell/string_utils.py
src/util/__init__.py
src/util/humanreadable.py
src/util/logger.py
xsim.egg-info/PKG-INFO
xsim.egg-info/SOURCES.txt
xsim.egg-info/dependency_links.txt
xsim.egg-info/entry_points.txt
xsim.egg-info/requires.txt
xsim.egg-info/top_level.txt